albula/__init__.py
albula/cleanup.py
albula/controller.py
albula/db.py
albula/main.py
albula/web.py
albula/apis/__init__.py
albula/apis/subsonic.py
albula/data_files/settings/default.ini
albula/dbbuild/__init__.py
albula/dbbuild/malojareader.py
albula/dbbuild/parser.py
albula/dbbuild/pruner.py
albula/dbbuild/scanner.py
albula/static/css/style.css
albula/static/ico/favicon.ico
albula/static/ico/favicon.png
albula/static/ico/favicon.xcf
albula/static/js/database.js
albula/static/js/howler.js
albula/static/js/linkintercept.js
albula/static/js/links.js
albula/static/js/neopolitan.js
albula/static/js/player.js
albula/static/js/view.js
albula/static/less/grisons.less
albula/static/less/grisonsfont.less
albula/static/less/style.less
albula/static/png/listadd.png
albula/static/png/listinsert.png
albula/static/png/next.png
albula/static/png/pause.png
albula/static/png/play.png
albula/static/png/prev.png
albula/static/png/unknown_album.png
albula/static/png/unknown_artist.png
albula/static/png/unknown_track.png
albula/static/svg/action_refreshmetadata.svg
albula/static/svg/action_scanlibrary.svg
albula/static/svg/play_radio.svg
albula/static/svg/play_random.svg
albula/static/svg/sort_alphabet.svg
albula/static/svg/sort_duration.svg
albula/static/svg/sort_lastplayed.svg
albula/static/svg/sort_love.svg
albula/static/svg/source.txt
albula/web/main.pyhp
albula/web/common/head.html
albula-0.5.4.dist-info/LICENSE
albula-0.5.4.dist-info/METADATA
albula-0.5.4.dist-info/WHEEL
albula-0.5.4.dist-info/entry_points.txt
albula-0.5.4.dist-info/top_level.txt
albula-0.5.4.dist-info/RECORD
